femtoQ/__init__.py
femtoQ/debuggingTests.py
femtoQ/fft_benchmark.py
femtoQ/plotting.py
femtoQ/plotting_example.py
femtoQ/pulse_retrieval.py
femtoQ/simulate_pulse_retrieval.py
femtoQ/tools.py
femtoQ/pr_backend/__init__.py
femtoQ/pr_backend/dscanlib.py
femtoQ/pr_backend/froglib.py
femtoQ/pr_backend/tdsilib.py
pypret/__init__.py
pypret/autocorrelation.py
pypret/fourier.py
pypret/frequencies.py
pypret/graphics.py
pypret/lib.py
pypret/material.py
pypret/mesh_data.py
pypret/pnps.py
pypret/pulse.py
pypret/pulse_error.py
pypret/random_pulse.py
pypret/io/__init__.py
pypret/io/handlers.py
pypret/io/io.py
pypret/io/options.py
pypret/retrieval/__init__.py
pypret/retrieval/nlo_retriever.py
pypret/retrieval/retriever.py
pypret/retrieval/step_retriever.py
femtoMod-4.0.0.dist-info/METADATA
femtoMod-4.0.0.dist-info/WHEEL
femtoMod-4.0.0.dist-info/top_level.txt
femtoMod-4.0.0.dist-info/RECORD
