Metadata-Version: 2.1
Name: femtoMod
Version: 4.0.0
Summary: femtoQ Modules
Home-page: https://github.com/UltraFastQ/Modules
Author: Patrick, Benjamin, Etienne
Author-email: UNKNOWN
License: UNKNOWN
Platform: UNKNOWN
Classifier: Programming Language :: Python :: 3
Classifier: License :: OSI Approved :: MIT License
Classifier: Operating System :: OS Independent
